[
  {
    "firstname": "Sherif Mohamed Ibrahim",
    "lastname": "Abdelfattah"
  },
  {
    "firstname": "Eric L",
    "lastname": "Brown"
  },
  {
    "firstname": "Katherine E",
    "lastname": "Brown"
  },
  {
    "firstname": "Travis S",
    "lastname": "Brummett"
  },
  {
    "firstname": "April Renee",
    "lastname": "Crockett"
  },
  {
    "firstname": "William Fred",
    "lastname": "Eberle"
  },
  {
    "firstname": "David W",
    "lastname": "Elizandro"
  },
  {
    "firstname": "Cyril Jason",
    "lastname": "Focht"
  },
  {
    "firstname": "Barbara",
    "lastname": "Gannod"
  },
  {
    "firstname": "Gerald C",
    "lastname": "Gannod"
  },
  {
    "firstname": "Sheikh Khaled",
    "lastname": "Ghafoor"
  },
  {
    "firstname": "Maanak",
    "lastname": "Gupta"
  },
  {
    "firstname": "Md Toufiqul",
    "lastname": "Islam"
  },
  {
    "firstname": "Beata",
    "lastname": "Kubiak"
  },
  {
    "firstname": "Md. Golam Moula",
    "lastname": "Mehedi Hasan"
  },
  {
    "firstname": "Muhammad Ismail Muhammad",
    "lastname": "Muhammad"
  },
  {
    "firstname": "Stacy",
    "lastname": "Prowell"
  },
  {
    "firstname": "Akond Ashfaque Ur",
    "lastname": "Rahman"
  },
  {
    "firstname": "Michael David",
    "lastname": "Rogers"
  },
  {
    "firstname": "Stephen Lucien",
    "lastname": "Scott"
  },
  {
    "firstname": "Susmit",
    "lastname": "Shannigrahi"
  },
  {
    "firstname": "Ambareen",
    "lastname": "Siraj"
  },
  {
    "firstname": "Douglas Alan",
    "lastname": "Talbert"
  },
  {
    "firstname": "Denis A",
    "lastname": "Ulybyshev"
  },
  {
    "firstname": null,
    "lastname": null
  },
  {
    "firstname": null,
    "lastname": null
  },
  {
    "firstname": null,
    "lastname": null
  },
  {
    "firstname": null,
    "lastname": null
  },
  {
    "firstname": null,
    "lastname": null
  }
]